gadutils/__init__.py
gadutils/binaries.py
gadutils/dates.py
gadutils/decimals.py
gadutils/fields.py
gadutils/json.py
gadutils/lists.py
gadutils/modules.py
gadutils/paths.py
gadutils/streams.py
gadutils/strings.py
gadutils/temp.py
gadutils/urls.py
gadutils/const/__init__.py
gadutils/const/encoding.py
gadutils/const/regexp.py
gadutils/const/symbols.py
gadutils/const/unicode.py
tests/__init__.py
tests/test_init.py
gadutils-0.0.3.dist-info/LICENSE
gadutils-0.0.3.dist-info/METADATA
gadutils-0.0.3.dist-info/WHEEL
gadutils-0.0.3.dist-info/top_level.txt
gadutils-0.0.3.dist-info/RECORD
